examples/__init__.py
examples/NotebookExample/__init__.py
examples/NotebookExample/Car/__init__.py
examples/NotebookExample/SteelIndustry/__init__.py
examples/NotebookExample/SteelIndustry/admodel.py
examples/NotebookExample/감염병/__init__.py
examples/Projects/__init__.py
examples/Projects/use_models_test.py
examples/Projects/AD_Folder/AD1.py
examples/Projects/AD_Folder/__init__.py
examples/Projects/BD_Folder/BD1.py
examples/Projects/BD_Folder/__init__.py
examples/Projects/RE_Folder/RE1.py
examples/Projects/RE_Folder/__init__.py
examples/Text2Models/__init__.py
examples/Text2Models/text_2_action_model_test.py
examples/Text2Models/text_2_sys_model_test.py
sysmpy/__init__.py
sysmpy/entity.py
sysmpy/entity_db.py
sysmpy/interface_analyzer.py
sysmpy/matrix_for_graph.py
sysmpy/model_generator.py
sysmpy/relationship.py
sysmpy/script_generator.py
sysmpy/script_to_model.py
sysmpy/sms_searcher.py
sysmpy/util.py
sysmpy/gui/__init__.py
sysmpy/gui/gui_main.py
sysmpy/gui/gui_mxgraph.py
sysmpy/gui/gui_mxgraph_action_diagram.py
sysmpy/gui/gui_mxgraph_block_diagram.py
sysmpy/gui/gui_mxgraph_hierarchy_diagram.py
SysMPy-0.0.9.dist-info/LICENSE
SysMPy-0.0.9.dist-info/METADATA
SysMPy-0.0.9.dist-info/WHEEL
SysMPy-0.0.9.dist-info/top_level.txt
SysMPy-0.0.9.dist-info/RECORD
