Metadata-Version: 2.1
Name: SysMPy
Version: 0.0.9
Summary: A library for System Modeling Runtime Environment (SMRE)
Home-page: https://github.com/pcyoung75/SysMPy
Author: SysMPy Team
Author-email: pcyoung75@gmail.com
License: Apache License Version 2.0
Platform: UNKNOWN
Classifier: Programming Language :: Python :: 3
Classifier: Operating System :: OS Independent
Requires-Python: >=3.7
